datetime3/__init__.py
datetime3-3.8.0.dist-info/LICENSE
datetime3-3.8.0.dist-info/METADATA
datetime3-3.8.0.dist-info/WHEEL
datetime3-3.8.0.dist-info/top_level.txt
datetime3-3.8.0.dist-info/RECORD
