Metadata-Version: 1.2
Name: datetime3
Version: 3.8.0
Summary: Latest Python 3.x datetime module packaged for use on older Python
Home-page: https://github.com/orent/datetime3
Author: packaged by Oren Tirosh
Author-email: orent@hishome.net
License: UNKNOWN
Platform: UNKNOWN
Classifier: Programming Language :: Python :: 3
Classifier: License :: OSI Approved :: Python Software Foundation License
Classifier: Operating System :: OS Independent
Requires-Python: >=3.0
